LICENSE
MANIFEST.in
README.md
requirements.txt
setup.py
django_static_respond/__init__.py
django_static_respond/admin.py
django_static_respond/apps.py
django_static_respond/models.py
django_static_respond/tests.py
django_static_respond/views.py
django_static_respond.egg-info/PKG-INFO
django_static_respond.egg-info/SOURCES.txt
django_static_respond.egg-info/dependency_links.txt
django_static_respond.egg-info/not-zip-safe
django_static_respond.egg-info/top_level.txt
django_static_respond/migrations/__init__.py
django_static_respond/static/respond/respond.matchmedia.addListener.min.js
django_static_respond/static/respond/respond.matchmedia.addListener.src.js
django_static_respond/static/respond/respond.min.js
django_static_respond/static/respond/respond.src.js